{
  "owner_address": "1FkazSE1BdZXHDHhtkuhr56sEfou7Ha1Ha",
  "profile": {
    "avatar": {
      "url": "https://s3.amazonaws.com/kd4/insanemoe"
    },
    "bio": "Graphic Designer - Making #ASketchaDay\r\nDesign Zombie - Podcast Addict - Music Junkie - Food Lover\r\nContact : insanemoe@gmail.com",
    "bitcoin": {
      "address": "1FuzKbKXbSqMp9urxyxEqa9qp79a4TMngy"
    },
    "cover": {
      "url": "https://s3.amazonaws.com/dx3/insanemoe"
    },
    "facebook": {
      "proof": {
        "url": "https://facebook.com/insanemoedesign/posts/10152752012114396"
      },
      "username": "insanemoedesign"
    },
    "github": {
      "proof": {
        "url": "https://gist.github.com/insanemoe/9f997422251532861644"
      },
      "username": "insanemoe"
    },
    "graph": {
      "url": "https://s3.amazonaws.com/grph/insanemoe"
    },
    "location": {
      "formatted": "Saint-Hubert"
    },
    "name": {
      "formatted": "Mauricio Gomez"
    },
    "twitter": {
      "proof": {
        "url": "https://twitter.com/Insanemoe/status/511948537278386176"
      },
      "username": "Insanemoe"
    },
    "v": "0.2",
    "website": "https://www.facebook.com/insanemoedesign"
  },
  "verifications": [
    {
      "identifier": "insanemoe",
      "proof_url": "https://gist.github.com/insanemoe/9f997422251532861644",
      "service": "github",
      "valid": true
    },
    {
      "identifier": "Insanemoe",
      "proof_url": "https://twitter.com/Insanemoe/status/511948537278386176",
      "service": "twitter",
      "valid": true
    },
    {
      "identifier": "insanemoedesign",
      "proof_url": "https://facebook.com/insanemoedesign/posts/10152752012114396",
      "service": "facebook",
      "valid": false
    }
  ]
}
