{
  "owner_address": "15d3mTo5QAaXmYEUQhkhNqo6yHcTaeC7mP",
  "profile": {
    "@type": "Person",
    "account": [
      {
        "@type": "Account",
        "identifier": "JeffHowerton",
        "proofType": "http",
        "proofUrl": "https://gist.github.com/JeffHowerton/d867c5f7b88a40b3c45565ce9f08178f",
        "service": "github"
      }
    ],
    "image": [
      {
        "@type": "ImageObject",
        "contentUrl": "https://s3.amazonaws.com/97p/wkj.jpeg",
        "name": "cover"
      }
    ]
  },
  "verifications": [
    {
      "identifier": "JeffHowerton",
      "proof_url": "https://gist.github.com/JeffHowerton/d867c5f7b88a40b3c45565ce9f08178f",
      "service": "github",
      "valid": true
    }
  ],
  "zone_file": "$ORIGIN jhonename.id\n$TTL 3600\n_http._tcp URI 10 1 \"https://blockstack.s3.amazonaws.com/jhonename.id\"\n"
}
