{
  "owner_address": "12GPuSk6jqBa8Q8WPcV1WSr1wvXagxqyxu",
  "profile": {
    "avatar": {
      "url": "https://s3.amazonaws.com/kd4/tracykuhrt"
    },
    "bio": "Software architect following technology and local businesses.",
    "bitcoin": {
      "address": "1DdS1UzrRLbY37SoKiFpb4fwtntH9k3MtV"
    },
    "cover": {
      "url": "https://s3.amazonaws.com/dx3/tracykuhrt"
    },
    "location": {
      "formatted": "Apache Junction, Arizona"
    },
    "name": {
      "formatted": "Tracy Kuhrt"
    },
    "twitter": {
      "username": "TracyKuhrt"
    },
    "v": "0.2"
  },
  "verifications": []
}
