{
  "owner_address": "1Jk2ZVZFpFsd8MReJDYDvpWS81sDieLw7x",
  "profile": {
    "avatar": {
      "url": "https://s3.amazonaws.com/kd4/mrdavenport"
    },
    "bio": "Designer at @Vine. Previously: @Foursquare & @SwarmApp. A friend at @madebyfriendsco. I like sweet tea and chicken biscuits.",
    "cover": {
      "url": "https://s3.amazonaws.com/97p/OSA.jpeg"
    },
    "location": {
      "formatted": "Queens, NY"
    },
    "name": {
      "formatted": "Zack Davenport"
    },
    "twitter": {
      "username": "mrdavenport"
    },
    "v": "0.2",
    "website": "http://www.mrdavenport.co"
  },
  "verifications": []
}
