{
  "owner_address": "19Yrtco1QTzbns5XuRch6uwfZTBKfrJT6",
  "profile": {
    "avatar": {
      "url": "https://s3.amazonaws.com/kd4/dion"
    },
    "bio": "Anything worth doing is worth overdoing.",
    "bitcoin": {
      "address": "12WM7JJzyCkUvE8ZH3fbnDko6Y9Z1DBrNu"
    },
    "cover": {
      "url": "https://s3.amazonaws.com/97p/lUU.jpeg"
    },
    "location": {
      "formatted": "London"
    },
    "name": {
      "formatted": "Dion"
    },
    "twitter": {
      "username": "d1on"
    },
    "v": "0.2"
  },
  "verifications": []
}
