{
  "owner_address": "1D2132fGJeWLai7xehYGFUtCU2Z4jngCZm",
  "profile": {
    "avatar": {
      "url": "https://s3.amazonaws.com/kd4/fredericlevaux"
    },
    "bio": "3x entrepreneur in Digital with exits, Now Chief Digital Officer @EY. Tweets are my own.",
    "cover": {
      "url": "https://s3.amazonaws.com/dx3/fredericlevaux"
    },
    "facebook": {
      "proof": {
        "url": "https://facebook.com/fredlevaux/posts/10153462161702635"
      },
      "username": "fredlevaux"
    },
    "location": {
      "formatted": "Paris"
    },
    "name": {
      "formatted": "fred_levaux"
    },
    "twitter": {
      "proof": {
        "url": "https://twitter.com/fred_levaux/status/694191934584328193"
      },
      "username": "fred_levaux"
    },
    "v": "0.2",
    "website": "http://www.ey.com"
  },
  "verifications": [
    {
      "identifier": "fred_levaux",
      "proof_url": "https://twitter.com/fred_levaux/status/694191934584328193",
      "service": "twitter",
      "valid": true
    },
    {
      "identifier": "fredlevaux",
      "proof_url": "https://facebook.com/fredlevaux/posts/10153462161702635",
      "service": "facebook",
      "valid": true
    }
  ]
}
