{
  "owner_address": "14FABz2yNA5KHjVkatTLzRgYUQrTALsfnt",
  "profile": {
    "avatar": {
      "url": "https://s3.amazonaws.com/kd4/toufique"
    },
    "bio": "I make local & social search engines by day, and sleep by night (sometimes).",
    "cover": {
      "url": "https://s3.amazonaws.com/97p/rv1.jpeg"
    },
    "location": {
      "formatted": "NY"
    },
    "name": {
      "formatted": "Toufique"
    },
    "twitter": {
      "username": "toufique"
    },
    "v": "0.2",
    "website": "http://labs.hugeinc.com/"
  },
  "verifications": []
}
