{
  "owner_address": "1KvTH5kMozPxJTF9k4FPUrF7EVoWKipbg1",
  "profile": {
    "avatar": {
      "url": "https://s3.amazonaws.com/kd4/kaler"
    },
    "bio": "Programmer/Entrepreneur/Actor/Model/Unreliable Narrator.\n\nI like iPhone, mobile, fashion, motorcycles, Vancouver, Canucks and I like you.\n\nWorking on @GoalyApp",
    "bitcoin": {},
    "cover": {
      "url": "https://s3.amazonaws.com/dx3/kaler"
    },
    "facebook": {
      "proof": {
        "url": "https://facebook.com/parveenkaler/posts/10100379433599983"
      },
      "username": "parveenkaler"
    },
    "github": {
      "proof": {
        "url": "https://gist.github.com/kaler/a5fafb7e3429a33f0cf0"
      },
      "username": "kaler"
    },
    "location": {
      "formatted": "The Republic of Vancouver"
    },
    "name": {
      "formatted": "Parveen Kaler"
    },
    "twitter": {
      "proof": {
        "url": "https://twitter.com/kaler/status/533321812549963776"
      },
      "username": "kaler"
    },
    "v": "0.2",
    "website": "http://about.me/kaler"
  },
  "verifications": [
    {
      "identifier": "kaler",
      "proof_url": "https://gist.github.com/kaler/a5fafb7e3429a33f0cf0",
      "service": "github",
      "valid": true
    },
    {
      "identifier": "kaler",
      "proof_url": "https://twitter.com/kaler/status/533321812549963776",
      "service": "twitter",
      "valid": true
    },
    {
      "identifier": "parveenkaler",
      "proof_url": "https://facebook.com/parveenkaler/posts/10100379433599983",
      "service": "facebook",
      "valid": false
    }
  ]
}
