{
  "owner_address": "1MopnuDeWLrAK853G9Ga29yCfETGVaVXyB",
  "profile": {
    "avatar": {
      "url": "https://s3.amazonaws.com/kd4/wompt"
    },
    "bio": "Social activist, futurist, optimist.",
    "cover": {
      "url": "https://s3.amazonaws.com/dx3/wompt"
    },
    "facebook": {
      "username": "i.poke.bears"
    },
    "location": {
      "formatted": "Portland, OR"
    },
    "name": {
      "formatted": "Josh Young"
    },
    "twitter": {
      "username": "JoshuaAdamYoung"
    },
    "v": "0.2"
  },
  "verifications": []
}
