{
  "owner_address": "12EwqVcqSykDJrSgjNCPz8W7j5MXdrnK9m",
  "profile": {
    "avatar": {
      "url": "https://s3.amazonaws.com/kd4/wouterbruijning"
    },
    "bio": "Maatschappelijk werker. Projectmanager Digitale Hulpverlening Kwadraad. Mede-eigenaar http://t.co/jYNWYmN1Da http://t.co/e7MEWKGV7M. Fotograaf",
    "cover": {
      "url": "https://s3.amazonaws.com/dx3/wouterbruijning"
    },
    "location": {
      "formatted": "Gouda"
    },
    "name": {
      "formatted": "Wouter Bruijning"
    },
    "twitter": {
      "proof": {
        "url": "https://twitter.com/wouterbruijning/status/685396265597808640"
      },
      "username": "WouterBruijning"
    },
    "v": "0.2",
    "website": "http://www.wouterbruijning.nl"
  },
  "verifications": [
    {
      "identifier": "WouterBruijning",
      "proof_url": "https://twitter.com/wouterbruijning/status/685396265597808640",
      "service": "twitter",
      "valid": true
    }
  ]
}
