{
  "owner_address": "13po3ySccXHj1DfDwcwzHXhuP6DiCibYHq",
  "profile": {
    "avatar": {
      "url": "https://s3.amazonaws.com/kd4/samin"
    },
    "bio": "Designer driven by curiosity for making things new & better. CD+co-founder @Nordkapp, #IxDAHel, co-chair #ixd16. Here mostly thinking out loud in 20/80 FI/EN.",
    "cover": {
      "url": "https://s3.amazonaws.com/dx3/samin"
    },
    "location": {
      "formatted": "Helsinki"
    },
    "name": {
      "formatted": "Sami Niemelä"
    },
    "twitter": {
      "username": "samin"
    },
    "v": "0.2",
    "website": "http://www.nordkapp.fi"
  },
  "verifications": []
}
