{
  "owner_address": "18kJMCuGiKvXc6Zp9FP1W63EoHmhZdygUx",
  "profile": {
    "avatar": {
      "url": "https://pbs.twimg.com/profile_images/435044835976691715/K6reSCch.jpeg"
    },
    "bio": "Entrepreneur - Motivator - Speaker - Musician - Internet Marketer - Musician -Fighter - Father of 2 Sons Contact: hello@sazeeb.com",
    "bitcoin": {
      "address": "1L1ku2T8cVKfeNovHEWwLHQEArjNAdCAKG"
    },
    "cover": {
      "url": "https://pbs.twimg.com/profile_banners/42383421/1398240616/web_retina"
    },
    "location": {
      "formatted": ""
    },
    "name": {
      "formatted": "Sazeeb"
    },
    "twitter": {
      "username": "Sazeeb"
    },
    "v": "0.2",
    "website": "http://www.sazeeb.com"
  },
  "verifications": []
}
