{
  "owner_address": "14Yh2YLq9nzb9eNmD4BeaxznG1aZZ6SGsX",
  "profile": {
    "cover": {
      "url": "https://s3.amazonaws.com/97p/OSA.jpeg"
    },
    "github": {
      "proof": {
        "url": "https://gist.github.com/DeviantdVeloper/d51351ee7e0afb603a6b"
      },
      "username": "DeviantdVeloper"
    },
    "location": {
      "formatted": "Smutland"
    },
    "name": {
      "formatted": "dVeloper"
    },
    "twitter": {
      "proof": {
        "url": "https://twitter.com/DeviantDveloper/status/698097694900822016"
      },
      "username": "DeviantDveloper"
    },
    "v": "0.2"
  },
  "verifications": [
    {
      "identifier": "DeviantdVeloper",
      "proof_url": "https://gist.github.com/DeviantdVeloper/d51351ee7e0afb603a6b",
      "service": "github",
      "valid": true
    },
    {
      "identifier": "DeviantDveloper",
      "proof_url": "https://twitter.com/DeviantDveloper/status/698097694900822016",
      "service": "twitter",
      "valid": false
    }
  ]
}
