{
  "owner_address": "16gEDHnsPaGyzg2MvsWGnZhgGUtKNzx8Kc",
  "profile": {
    "avatar": {
      "url": "https://s3.amazonaws.com/kd4/ferdinandreyes"
    },
    "bio": "Couchsurfer. P2P. Rural-techie. Photography. Sociocultural Animator.  Writing in @bitcoinmagazine - #viladeflix, #Tarragona & #Sicilia",
    "bitcoin": {
      "address": "1Nc1ot1SJQggBWk4NfzdCrwVgbevw2YWVW"
    },
    "cover": {
      "url": "https://s3.amazonaws.com/dx3/ferdinandreyes"
    },
    "location": {
      "formatted": "ferdinandreyes.tumblr.com"
    },
    "name": {
      "formatted": "Ferdinand Reyes"
    },
    "twitter": {
      "proof": {
        "url": "https://twitter.com/prefiguractivo/status/521618251420168192"
      },
      "username": "prefiguractivo"
    },
    "v": "0.2"
  },
  "verifications": [
    {
      "identifier": "prefiguractivo",
      "proof_url": "https://twitter.com/prefiguractivo/status/521618251420168192",
      "service": "twitter",
      "valid": false
    }
  ]
}
