{
  "owner_address": "1Q8x25aB9xsqgZYzTfmH3A37NggLbe1N1e",
  "profile": {
    "avatar": {
      "url": "https://s3.amazonaws.com/kd4/roybahat"
    },
    "bio": "Head of @BloombergBeta, a new fund that invests and makes things -- backed by @BloombergLP. And always @playouya backer zero. Alignment: Neutral good.",
    "bitcoin": {
      "address": "1FeAzVbDjSHqDg8t7AoF5twUTz88f6TB7q"
    },
    "cover": {
      "url": "https://s3.amazonaws.com/dx3/roybahat"
    },
    "github": {
      "proof": {
        "url": "https://gist.github.com/roybahat/fb0321f39c3bd6517ac4"
      },
      "username": "roybahat"
    },
    "location": {
      "formatted": "San Francisco"
    },
    "name": {
      "formatted": "Roy Bahat"
    },
    "twitter": {
      "username": "roybahat"
    },
    "v": "0.2",
    "website": "http://also.roybahat.com"
  },
  "verifications": [
    {
      "identifier": "roybahat",
      "proof_url": "https://gist.github.com/roybahat/fb0321f39c3bd6517ac4",
      "service": "github",
      "valid": true
    }
  ]
}
