{
  "owner_address": "18ZBgD1umE8W4br5k6GoJXeebrtMuptNLH",
  "profile": {
    "avatar": {
      "url": "https://s3.amazonaws.com/kd4/aniol"
    },
    "bitcoin": {
      "address": "1Ak7b7vHfAB3cgzAGPFCrKkM98Zdd3FgLj"
    },
    "cover": {
      "url": "https://s3.amazonaws.com/97p/rv1.jpeg"
    },
    "github": {
      "proof": {
        "url": "https://gist.github.com/aniol/9ceefed4679782a9b2f5"
      },
      "username": "aniol"
    },
    "graph": {
      "url": "https://s3.amazonaws.com/grph/aniol"
    },
    "location": {
      "formatted": "Ohtori"
    },
    "name": {
      "formatted": "Aniol"
    },
    "twitter": {
      "proof": {
        "url": "https://twitter.com/aniol/status/525954522716196864"
      },
      "username": "aniol"
    },
    "v": "0.2",
    "website": "http://about.me/aniol"
  },
  "verifications": [
    {
      "identifier": "aniol",
      "proof_url": "https://gist.github.com/aniol/9ceefed4679782a9b2f5",
      "service": "github",
      "valid": false
    },
    {
      "identifier": "aniol",
      "proof_url": "https://twitter.com/aniol/status/525954522716196864",
      "service": "twitter",
      "valid": true
    }
  ]
}
