{
  "owner_address": "1DeJCV5gHUf5GXVR2dmBETjie3KDQgcssF",
  "profile": "{\"account\": [{\"@type\": \"Account\", \"identifier\": \"2e01d1d41e5cdee4f4add54f99f1ac3bafda0ff5\", \"service\": \"openbazaar\"}], \"bitcoin\": {\"address\": \"1KStptmvS95uDa5KHWQGwbBHGnquJ2QzzT\"}, \"name\": {\"formatted\": \"Dekker3D\"}, \"pgp\": {\"fingerprint\": \"\", \"url\": \"\"}, \"v\": \"0.2\", \"website\": \"http://www.dekker3d.com\"}",
  "verifications": [],
  "zone_file": "{\"account\": [{\"@type\": \"Account\", \"identifier\": \"2e01d1d41e5cdee4f4add54f99f1ac3bafda0ff5\", \"service\": \"openbazaar\"}], \"bitcoin\": {\"address\": \"1KStptmvS95uDa5KHWQGwbBHGnquJ2QzzT\"}, \"name\": {\"formatted\": \"Dekker3D\"}, \"pgp\": {\"fingerprint\": \"\", \"url\": \"\"}, \"v\": \"0.2\", \"website\": \"http://www.dekker3d.com\"}"
}
