{
  "owner_address": "1QDHz43iUCrg5Hze6tBkFbcDHc15xetbRg",
  "profile": {
    "avatar": {
      "url": "https://s3.amazonaws.com/kd4/thomreagan"
    },
    "bio": "Pastor, Christian, Father, Productivity and Efficiency Guy, High-Tech Redneck, NASCAR fan, BBQer, stumbling through life.",
    "cover": {
      "url": "https://s3.amazonaws.com/dx3/thomreagan"
    },
    "facebook": {
      "username": "SpeakerThomReagan"
    },
    "location": {
      "formatted": "Doe Run, MO"
    },
    "name": {
      "formatted": "Thom Reagan"
    },
    "twitter": {
      "proof": {
        "url": "https://twitter.com/thomreagan/status/715587858355122176"
      },
      "username": "thomreagan"
    },
    "v": "0.2",
    "website": "http://www.ThomReagan.com"
  },
  "verifications": [
    {
      "identifier": "thomreagan",
      "proof_url": "https://twitter.com/thomreagan/status/715587858355122176",
      "service": "twitter",
      "valid": true
    }
  ]
}
