{
  "owner_address": "1GBxFGXCnixSeQnfgTTmDWdH8xnUgpt8Wo",
  "profile": {
    "avatar": {
      "url": "https://s3.amazonaws.com/kd4/yules"
    },
    "bio": "Build stuff. Tear it apart. Repeat. VP R&D for LightApp tech.",
    "bitcoin": {
      "address": "13XbyydDRVytBFK8ymxqmU1JoUBp7hoJk6"
    },
    "cover": {
      "url": "https://s3.amazonaws.com/dx3/yules"
    },
    "facebook": {
      "proof": {
        "url": "https://facebook.com/yuval.leshem/posts/10153944955627516"
      },
      "username": "yuval.leshem"
    },
    "github": {
      "proof": {
        "url": "https://gist.github.com/anonymous/4b6605034d44ec9591f2"
      },
      "username": "anonymous"
    },
    "graph": {
      "url": "https://s3.amazonaws.com/grph/yules"
    },
    "location": {
      "formatted": "Dizzy Suburbia "
    },
    "name": {
      "formatted": "Yuval Leshem"
    },
    "twitter": {
      "proof": {
        "url": "https://twitter.com/Yulesh/status/536588077846650880"
      },
      "username": "Yulesh"
    },
    "v": "0.2",
    "website": "http://www.yules.co"
  },
  "verifications": [
    {
      "identifier": "anonymous",
      "proof_url": "https://gist.github.com/anonymous/4b6605034d44ec9591f2",
      "service": "github",
      "valid": true
    },
    {
      "identifier": "Yulesh",
      "proof_url": "https://twitter.com/Yulesh/status/536588077846650880",
      "service": "twitter",
      "valid": true
    },
    {
      "identifier": "yuval.leshem",
      "proof_url": "https://facebook.com/yuval.leshem/posts/10153944955627516",
      "service": "facebook",
      "valid": true
    }
  ]
}
