{
  "owner_address": "1MWYGpwaLYRFBX8qvM8F6JeP9GihPpjqva",
  "profile": {
    "avatar": {
      "url": "https://s3.amazonaws.com/kd4/oneolivier"
    },
    "bio": "",
    "cover": {
      "url": "https://s3.amazonaws.com/dx3/oneolivier"
    },
    "location": {
      "formatted": "A l'ouest"
    },
    "name": {
      "formatted": "Olivier"
    },
    "twitter": {
      "proof": {
        "url": "https://twitter.com/olivr/status/694156691294785536"
      },
      "username": "olivr"
    },
    "v": "0.2",
    "website": "http://flavors.me/olivr"
  },
  "verifications": [
    {
      "identifier": "olivr",
      "proof_url": "https://twitter.com/olivr/status/694156691294785536",
      "service": "twitter",
      "valid": true
    }
  ]
}
