{
  "owner_address": "1Kov8FGQSgsbrZTVorpUC4k22YnhuLto2D",
  "profile": {
    "avatar": {
      "url": "https://s3.amazonaws.com/kd4/aurelierida"
    },
    "bio": "Cycliste par tous les temps, Geekette, Juriste, Soc' en direct de l'Assemblée",
    "cover": {
      "url": "https://s3.amazonaws.com/97p/lUU.jpeg"
    },
    "facebook": {
      "proof": {
        "url": "https://facebook.com/aurelie.rida/posts/10153324950215069"
      },
      "username": "aurelie.rida"
    },
    "location": {
      "formatted": "Paris"
    },
    "name": {
      "formatted": "Aurélie"
    },
    "twitter": {
      "proof": {
        "url": "https://twitter.com/AurelieRC/status/694178690788409348"
      },
      "username": "AurelieRC"
    },
    "v": "0.2"
  },
  "verifications": [
    {
      "identifier": "AurelieRC",
      "proof_url": "https://twitter.com/AurelieRC/status/694178690788409348",
      "service": "twitter",
      "valid": true
    },
    {
      "identifier": "aurelie.rida",
      "proof_url": "https://facebook.com/aurelie.rida/posts/10153324950215069",
      "service": "facebook",
      "valid": false
    }
  ]
}
