{
  "owner_address": "19YdeaDKZhcs7FhZ9BU9sqxRL9EPzM9Ljr",
  "profile": {
    "avatar": {
      "url": "https://s3.amazonaws.com/kd4/leonieke"
    },
    "bio": "Of course I have played outdoor games. I once played dominoes in an open air cafe in Paris. ~Oscar Wilde | Platform Manager Books&Journals, Koninklijke Brill NV",
    "cover": {
      "url": "https://s3.amazonaws.com/dx3/leonieke"
    },
    "github": {
      "proof": {
        "url": "https://gist.github.com/leonieke/cc0e2c3311915caa3508"
      },
      "username": "leonieke"
    },
    "location": {
      "formatted": "Den Haag, Nederland"
    },
    "name": {
      "formatted": "Leonieke Aalders"
    },
    "twitter": {
      "proof": {
        "url": "https://twitter.com/leonieke/status/686665470146146304"
      },
      "username": "leonieke"
    },
    "v": "0.2",
    "website": "http://leonieke.eu"
  },
  "verifications": [
    {
      "identifier": "leonieke",
      "proof_url": "https://gist.github.com/leonieke/cc0e2c3311915caa3508",
      "service": "github",
      "valid": true
    },
    {
      "identifier": "leonieke",
      "proof_url": "https://twitter.com/leonieke/status/686665470146146304",
      "service": "twitter",
      "valid": true
    }
  ]
}
