{
  "owner_address": "12d4v5VbtmhdL2Xybw252aYLjGC2AT2vPR",
  "profile": {
    "avatar": {
      "url": "https://s3.amazonaws.com/kd4/mitterer"
    },
    "cover": {
      "url": "https://s3.amazonaws.com/97p/L2N.jpeg"
    },
    "facebook": {
      "proof": {
        "url": "https://facebook.com/rickmitterer/posts/10153835017437166"
      },
      "username": "rickmitterer"
    },
    "location": {
      "formatted": "Miami Beach, Fl."
    },
    "name": {
      "formatted": "rmitterer"
    },
    "twitter": {
      "proof": {
        "url": "https://twitter.com/rmitterer/status/598954346076872705"
      },
      "username": "rmitterer"
    },
    "v": "0.2"
  },
  "verifications": [
    {
      "identifier": "rmitterer",
      "proof_url": "https://twitter.com/rmitterer/status/598954346076872705",
      "service": "twitter",
      "valid": true
    },
    {
      "identifier": "rickmitterer",
      "proof_url": "https://facebook.com/rickmitterer/posts/10153835017437166",
      "service": "facebook",
      "valid": false
    }
  ]
}
