{
  "owner_address": "1AcHoBbuKNjRGWAo2kQpWcnWkdz7fYM5Sz",
  "profile": {
    "bitcoin": {
      "address": "1E8EoDcQegUjc1xyv3GbkP6W219DNgbDoq"
    },
    "cover": {
      "url": "https://s3.amazonaws.com/97p/rv1.jpeg"
    },
    "facebook": {
      "proof": {
        "url": "https://facebook.com/olivier guitard/posts/10205391215726428"
      },
      "username": "olivier guitard"
    },
    "name": {
      "formatted": "Olivier Guitard"
    },
    "pgp": {
      "fingerprint": "31750443A10237499F2B2C20C6EDBAE7A865F6FE",
      "url": "https://s3.amazonaws.com/pk9/olivier_guitard"
    },
    "v": "0.2"
  },
  "verifications": [
    {
      "identifier": "olivier guitard",
      "proof_url": "https://facebook.com/olivier guitard/posts/10205391215726428",
      "service": "facebook",
      "valid": false
    }
  ]
}
