{
  "owner_address": "1LPi9Jvxke5K1w8gApZ5ByJLZpKPmzYehq",
  "profile": {
    "avatar": {
      "url": "https://s3.amazonaws.com/kd4/oliviertripet"
    },
    "bio": "Consultant and Trainer on Social Media, Community Management and Enterprise 2.0 // Cofounder of @net_academy // Founder and President of @scma_",
    "bitcoin": {
      "address": "1NxfRkwM89gSNVRVBtbMcGkc1rttvHBVUC"
    },
    "cover": {
      "url": "https://s3.amazonaws.com/97p/ikZ.jpeg"
    },
    "facebook": {
      "proof": {
        "url": "https://facebook.com/tripet/posts/10155319268595096"
      },
      "username": "tripet"
    },
    "graph": {
      "url": "https://s3.amazonaws.com/grph/oliviertripet"
    },
    "location": {
      "formatted": "Switzerland"
    },
    "name": {
      "formatted": "Olivier Tripet"
    },
    "twitter": {
      "proof": {
        "url": "https://twitter.com/oliviertripet/status/567248782178668545"
      },
      "username": "oliviertripet"
    },
    "v": "0.2",
    "website": "http://oliviertripet.com/"
  },
  "verifications": [
    {
      "identifier": "oliviertripet",
      "proof_url": "https://twitter.com/oliviertripet/status/567248782178668545",
      "service": "twitter",
      "valid": true
    },
    {
      "identifier": "tripet",
      "proof_url": "https://facebook.com/tripet/posts/10155319268595096",
      "service": "facebook",
      "valid": true
    }
  ]
}
