{
  "owner_address": "1BEMBHjco1C1vXWYuZpALZNGPU8aqtkUp",
  "profile": {
    "avatar": {
      "url": "https://s3.amazonaws.com/kd4/paulverhoeven"
    },
    "bio": "You can't stop what can't be stopped",
    "cover": {
      "url": "https://s3.amazonaws.com/dx3/paulverhoeven"
    },
    "location": {
      "formatted": "EHV '75, XV '73, B&D, NB, NL"
    },
    "name": {
      "formatted": "Paul Verhoeven"
    },
    "twitter": {
      "username": "iH8"
    },
    "v": "0.2",
    "website": "http://iH8.nl"
  },
  "verifications": []
}
