{
  "owner_address": "14iXy2bAmsVyvCe5ZxyCWPCDvNgFbQ9arx",
  "profile": {
    "avatar": {
      "url": "https://s3.amazonaws.com/kd4/pkeane"
    },
    "bio": "Pres. Sharethrough. Investor. Bleacher Report, OnSwipe, lobsterman. Former CEO: Associated Content. Former Google, CBS, Jupiter Research.",
    "bitcoin": {
      "address": "19VKZpyPv8whMrjTFdQJHk63ght7BGGgJ4"
    },
    "cover": {
      "url": "https://s3.amazonaws.com/dx3/pkeane"
    },
    "location": {
      "formatted": "NYC"
    },
    "name": {
      "formatted": "Patrick Keane"
    },
    "twitter": {
      "username": "phkeane"
    },
    "v": "0.2",
    "website": "http://sharethrough.com"
  },
  "verifications": []
}
