{
  "owner_address": "12wQhmcqsLnRpLz8xwxneTCTJDmcgNHEr4",
  "profile": {
    "avatar": {
      "url": "https://s3.amazonaws.com/kd4/jimnguyen"
    },
    "bio": "Product guy, BD @PayPal",
    "bitcoin": {
      "address": "15St6zwPzz8bNTs6h6CubU23THR3WRwEwW"
    },
    "cover": {
      "url": "https://s3.amazonaws.com/97p/Ov8.jpg"
    },
    "facebook": {
      "proof": {
        "url": "https://facebook.com/jimnguyen.jn/posts/10205073741821516"
      },
      "username": "jimnguyen.jn"
    },
    "location": {
      "formatted": "Palo Alto"
    },
    "name": {
      "formatted": "Jim Nguyen"
    },
    "twitter": {
      "proof": {
        "url": "https://twitter.com/jimnguyenjn/status/544997748815036416"
      },
      "username": "jimnguyenjn"
    },
    "v": "0.2"
  },
  "verifications": [
    {
      "identifier": "jimnguyenjn",
      "proof_url": "https://twitter.com/jimnguyenjn/status/544997748815036416",
      "service": "twitter",
      "valid": true
    },
    {
      "identifier": "jimnguyen.jn",
      "proof_url": "https://facebook.com/jimnguyen.jn/posts/10205073741821516",
      "service": "facebook",
      "valid": false
    }
  ]
}
