{
  "owner_address": "13iHUdbwdNQcEKQqDq9WQaHq3fswHrfMyD",
  "profile": {
    "avatar": {
      "url": "https://s3.amazonaws.com/kd4/davidssmith"
    },
    "bio": "I live for Bitcoin + Startups.\nhttp://t.co/VcxzD0qLIq & http://t.co/21mLMx0TXO",
    "bitcoin": {
      "address": "1JsWVMtRx5NvPn41AERcZA85aDw18LfD4m"
    },
    "cover": {
      "url": "https://s3.amazonaws.com/dx3/davidssmith"
    },
    "facebook": {
      "proof": {
        "url": "https://facebook.com/DavidSilvaSmith/posts/10107525831425314"
      },
      "username": "DavidSilvaSmith"
    },
    "github": {
      "proof": {
        "url": "https://gist.github.com/davidsilvasmith/df8460d2adce323641b4"
      },
      "username": "davidsilvasmith"
    },
    "location": {
      "formatted": "Lansing, MI"
    },
    "name": {
      "formatted": "David Silva Smith"
    },
    "twitter": {
      "proof": {
        "url": "https://twitter.com/DavidSilvaSmith/status/669498327004614656"
      },
      "username": "DavidSilvaSmith"
    },
    "v": "0.2",
    "website": "http://www.davidsilvasmith.com"
  },
  "verifications": [
    {
      "identifier": "davidsilvasmith",
      "proof_url": "https://gist.github.com/davidsilvasmith/df8460d2adce323641b4",
      "service": "github",
      "valid": true
    },
    {
      "identifier": "DavidSilvaSmith",
      "proof_url": "https://twitter.com/DavidSilvaSmith/status/669498327004614656",
      "service": "twitter",
      "valid": true
    },
    {
      "identifier": "DavidSilvaSmith",
      "proof_url": "https://facebook.com/DavidSilvaSmith/posts/10107525831425314",
      "service": "facebook",
      "valid": false
    }
  ]
}
