{
  "owner_address": "1AqHgJEZxJ4FnD8ZKNZSYHWWjAPTc1XEfx",
  "profile": {
    "avatar": {
      "url": "https://s3.amazonaws.com/kd4/sethpeterson"
    },
    "bio": "",
    "cover": {
      "url": "https://s3.amazonaws.com/97p/KJy.jpeg"
    },
    "facebook": {
      "username": "seth.peterson"
    },
    "location": {
      "formatted": "Raleigh, NC"
    },
    "name": {
      "formatted": "Seth Peterson"
    },
    "twitter": {
      "username": "sethpeterson"
    },
    "v": "0.2"
  },
  "verifications": []
}
