{
  "owner_address": "1LVvuPA8is7yijAnbWPpx2YMVQS2FTsryp",
  "profile": {
    "avatar": {
      "url": "https://s3.amazonaws.com/kd4/goga"
    },
    "bitcoin": {
      "address": "1CAPfQkkQtQSZf6qxADMSqX7DnpTJ6KyzS"
    },
    "cover": {
      "url": "https://s3.amazonaws.com/97p/483.jpeg"
    },
    "facebook": {
      "username": "dnaidionov"
    },
    "graph": {
      "url": "https://s3.amazonaws.com/grph/goga"
    },
    "location": {
      "formatted": ""
    },
    "name": {
      "formatted": "Dmitry Naidionov"
    },
    "twitter": {
      "proof": {
        "url": "https://twitter.com/gogafon/status/533503260934406144"
      },
      "username": "gogafon"
    },
    "v": "0.2"
  },
  "verifications": [
    {
      "identifier": "gogafon",
      "proof_url": "https://twitter.com/gogafon/status/533503260934406144",
      "service": "twitter",
      "valid": true
    }
  ]
}
