{
  "owner_address": "12qLqnjxpdtYAKkCYxuUPHX8HNmM3yiVh6",
  "profile": {
    "bitcoin": {
      "address": "164XvCxJ3frmNGGGWmKdGJecRDNx3CdrqY"
    },
    "cover": {
      "url": "https://s3.amazonaws.com/97p/F9g.jpg"
    },
    "facebook": {
      "proof": {
        "url": "https://facebook.com/IvanG11/posts/10208520087307506"
      },
      "username": "IvanG11"
    },
    "github": {
      "proof": {
        "url": "https://gist.github.com/IvanG11/4fc67252da54b0750581"
      },
      "username": "IvanG11"
    },
    "location": {
      "formatted": "Spain"
    },
    "name": {
      "formatted": "Iván García"
    },
    "twitter": {
      "proof": {
        "url": "https://twitter.com/ivng11/status/672401774255452160"
      },
      "username": "ivng11"
    },
    "v": "0.2"
  },
  "verifications": [
    {
      "identifier": "IvanG11",
      "proof_url": "https://gist.github.com/IvanG11/4fc67252da54b0750581",
      "service": "github",
      "valid": false
    },
    {
      "identifier": "ivng11",
      "proof_url": "https://twitter.com/ivng11/status/672401774255452160",
      "service": "twitter",
      "valid": false
    },
    {
      "identifier": "IvanG11",
      "proof_url": "https://facebook.com/IvanG11/posts/10208520087307506",
      "service": "facebook",
      "valid": false
    }
  ]
}
