{
  "owner_address": "1N5Tmka9TAdUnybBo3cdvtSreN7PjXMSHN",
  "profile": {
    "avatar": {
      "url": "https://pbs.twimg.com/profile_images/474041447780339714/FRzbUCso.jpeg"
    },
    "bio": "Volunteer, Web Developer ~ SEO Expert. Productive Muslim and Funjabi. I believe in success in this world and hereafter, through Quran and sunnah. #JOBless",
    "bitcoin": {
      "address": "13bnocNEcApuJHbBax947VYPWPYv9wGTui"
    },
    "cover": {
      "url": "https://s3.amazonaws.com/97p/HHE.jpg"
    },
    "location": {
      "formatted": "Faisalabad, Pakistan"
    },
    "name": {
      "formatted": "Abdul Rahman"
    },
    "twitter": {
      "proof": {
        "url": "https://twitter.com/pomy/status/488637447866028032"
      },
      "username": "pomy"
    },
    "v": "0.2",
    "website": "http://pomy.pk"
  },
  "verifications": [
    {
      "identifier": "pomy",
      "proof_url": "https://twitter.com/pomy/status/488637447866028032",
      "service": "twitter",
      "valid": true
    }
  ]
}
