{
  "owner_address": "1BbUWouSL4sUx8CFZaQW1dbrwPZD3vKU41",
  "profile": {
    "avatar": {
      "url": "https://s3.amazonaws.com/kd4/pullerits"
    },
    "bio": "Helping people transfer money, my team to build a great product and engineers to deliver faster at TransferWise.",
    "cover": {
      "url": "https://s3.amazonaws.com/97p/lUU.jpeg"
    },
    "location": {
      "formatted": "Tallinn"
    },
    "name": {
      "formatted": "Peep Pullerits"
    },
    "twitter": {
      "username": "pullerits"
    },
    "v": "0.2"
  },
  "verifications": []
}
