{
  "owner_address": "1LvTEmQPS7jhF3zVP4jJYtgicRJM2YUyqC",
  "profile": {
    "avatar": {
      "url": "https://s3.amazonaws.com/kd4/jcorioland"
    },
    "bio": "@Azure Technical Evangelist @Microsoft Tweeting about #Cloud, #microservices and #DevOps. Tweets are my own.",
    "cover": {
      "url": "https://s3.amazonaws.com/dx3/jcorioland"
    },
    "facebook": {
      "proof": {
        "url": "https://facebook.com/beedoo/posts/10153921142134696"
      },
      "username": "beedoo"
    },
    "github": {
      "proof": {
        "url": "https://gist.github.com/jcorioland/12abe81032de9867a26e"
      },
      "username": "jcorioland"
    },
    "location": {
      "formatted": "Paris"
    },
    "name": {
      "formatted": "Julien CORIOLAND"
    },
    "twitter": {
      "proof": {
        "url": "https://twitter.com/jcorioland/status/694275706394693632"
      },
      "username": "jcorioland"
    },
    "v": "0.2",
    "website": "https://blogs.msdn.microsoft.com/jcorioland"
  },
  "verifications": [
    {
      "identifier": "jcorioland",
      "proof_url": "https://gist.github.com/jcorioland/12abe81032de9867a26e",
      "service": "github",
      "valid": false
    },
    {
      "identifier": "jcorioland",
      "proof_url": "https://twitter.com/jcorioland/status/694275706394693632",
      "service": "twitter",
      "valid": false
    },
    {
      "identifier": "beedoo",
      "proof_url": "https://facebook.com/beedoo/posts/10153921142134696",
      "service": "facebook",
      "valid": false
    }
  ]
}
