{
  "owner_address": "1FnHkA8AF6tf9dNxRZMvPrucs45iw7PBQr",
  "profile": {
    "avatar": {
      "url": "https://s3.amazonaws.com/kd4/claartje13"
    },
    "bio": "Web/image editor, photography, graphic design, animals, drinks, hard work, France, Donald Duck, no kids, Achmea, wine including SWEN1",
    "cover": {
      "url": "https://s3.amazonaws.com/dx3/claartje13"
    },
    "location": {
      "formatted": "Amersfoort-Netherlands"
    },
    "name": {
      "formatted": "Claartje"
    },
    "twitter": {
      "username": "claartje13"
    },
    "v": "0.2",
    "website": "http://www.linkedin.com/in/claartjederidder"
  },
  "verifications": []
}
