{
  "owner_address": "1DcY6nbxkdaj92jjBBLHW5QZLH1iZKqepf",
  "profile": {
    "cover": {
      "url": "https://s3.amazonaws.com/97p/rv1.jpeg"
    },
    "name": {
      "formatted": "Marco Mat"
    },
    "twitter": {
      "proof": {
        "url": "https://twitter.com/matcomar/status/701737447093354496"
      },
      "username": "matcomar"
    },
    "v": "0.2"
  },
  "verifications": [
    {
      "identifier": "matcomar",
      "proof_url": "https://twitter.com/matcomar/status/701737447093354496",
      "service": "twitter",
      "valid": true
    }
  ],
  "zone_file": {}
}
