{
  "owner_address": "12KBPZpSF8YBG2eVwYe8yS9p2qy2A7o9M9",
  "profile": {
    "avatar": {
      "url": "https://s3.amazonaws.com/kd4/matthewhart"
    },
    "bitcoin": {
      "address": "1E278RjVEZvCSrsVNAuef2j99uU7GEghuP"
    },
    "cover": {
      "url": "https://s3.amazonaws.com/97p/IKM.jpeg"
    },
    "facebook": {
      "proof": {
        "url": "https://facebook.com/cmyplay/posts/10156042211580078"
      },
      "username": "cmyplay"
    },
    "github": {
      "proof": {
        "url": "https://gist.github.com/cmyplay/ca8e4cab0d4d3121b089"
      },
      "username": "cmyplay"
    },
    "location": {
      "formatted": "Johannesburg"
    },
    "name": {
      "formatted": "Matthew Hart"
    },
    "twitter": {
      "proof": {
        "url": "https://twitter.com/cmyplay/status/637898153845522432"
      },
      "username": "cmyplay"
    },
    "v": "0.2"
  },
  "verifications": [
    {
      "identifier": "cmyplay",
      "proof_url": "https://gist.github.com/cmyplay/ca8e4cab0d4d3121b089",
      "service": "github",
      "valid": true
    },
    {
      "identifier": "cmyplay",
      "proof_url": "https://twitter.com/cmyplay/status/637898153845522432",
      "service": "twitter",
      "valid": true
    },
    {
      "identifier": "cmyplay",
      "proof_url": "https://facebook.com/cmyplay/posts/10156042211580078",
      "service": "facebook",
      "valid": true
    }
  ]
}
