{
  "owner_address": "15Ljwxuwg49fJCx9aJGJE5dPZk5es6seP1",
  "profile": {
    "bitcoin": {
      "address": "16TuQLmLXnsL9XdKLkXsB5CxHD727ZZuZV"
    },
    "cover": {
      "url": "https://s3.amazonaws.com/dx3/maxt"
    },
    "facebook": {
      "proof": {
        "url": "https://facebook.com/maxtannahill/posts/10156088640690364"
      },
      "username": "maxtannahill"
    },
    "github": {
      "proof": {
        "url": "https://gist.github.com/maxtannahill/3e6a28685ae29f60b9f0"
      },
      "username": "maxtannahill"
    },
    "name": {
      "formatted": "Max Tannahill"
    },
    "pgp": {
      "fingerprint": "602234D3F520354C6AF511987610EEEFFD25FEC5",
      "url": "https://s3.amazonaws.com/pk9/maxt"
    },
    "twitter": {
      "proof": {
        "url": "https://twitter.com/maxtannahill/status/656102543542489088"
      },
      "username": "maxtannahill"
    },
    "v": "0.2"
  },
  "verifications": [
    {
      "identifier": "maxtannahill",
      "proof_url": "https://gist.github.com/maxtannahill/3e6a28685ae29f60b9f0",
      "service": "github",
      "valid": false
    },
    {
      "identifier": "maxtannahill",
      "proof_url": "https://twitter.com/maxtannahill/status/656102543542489088",
      "service": "twitter",
      "valid": false
    },
    {
      "identifier": "maxtannahill",
      "proof_url": "https://facebook.com/maxtannahill/posts/10156088640690364",
      "service": "facebook",
      "valid": false
    }
  ]
}
