{
  "owner_address": "191eQvjjhh3gUBF6frToAPNdqwpjUHXjrt",
  "profile": {
    "bio": "purwakarta",
    "bitcoin": {
      "address": "191eQvjjhh3gUBF6frToAPNdqwpjUHXjrt"
    },
    "cover": {
      "url": "https://s3.amazonaws.com/97p/northern-lights.jpg"
    },
    "location": {
      "formatted": "indonesia"
    },
    "name": {
      "formatted": "dede"
    },
    "twitter": {
      "username": "Aeroplane5"
    },
    "v": "0.2",
    "website": "http://kumpulan-skripsi-makalah.blogspot.com/"
  },
  "verifications": []
}
