{
  "owner_address": "15tEZAKo9Yt9dtoikofJ6JgyDVAzPQKPYy",
  "profile": {
    "bitcoin": {
      "address": "1ET74kdRxsJ6GbjK773Z3z3sDgPRUZePCh"
    },
    "cover": {
      "url": "https://s3.amazonaws.com/97p/4AL.jpeg"
    },
    "facebook": {
      "proof": {
        "url": "https://facebook.com/cheung.sinead/posts/10202852256702123"
      },
      "username": "cheung.sinead"
    },
    "v": "0.2"
  },
  "verifications": [
    {
      "identifier": "cheung.sinead",
      "proof_url": "https://facebook.com/cheung.sinead/posts/10202852256702123",
      "service": "facebook",
      "valid": false
    }
  ]
}
