{
  "owner_address": "1NpMJMHZTrT9jXGMaNeevH8UMemYHpEFAD",
  "profile": {
    "avatar": {
      "url": "https://s3.amazonaws.com/kd4/scottollivier"
    },
    "bio": "pursuing flow & balance",
    "bitcoin": {
      "address": "17ngaaCNBnVpDEhgJ3BX77brspsVxW8Ffr"
    },
    "cover": {
      "url": "https://s3.amazonaws.com/97p/2wu.jpeg"
    },
    "facebook": {
      "proof": {
        "url": "https://facebook.com/scott.ollivier/posts/10152901739289015"
      },
      "username": "scott.ollivier"
    },
    "github": {
      "proof": {
        "url": "https://gist.github.com/sjollivier/4bf6dce23197ce6efef0"
      },
      "username": "sjollivier"
    },
    "location": {
      "formatted": "So-Cen-NorCal"
    },
    "name": {
      "formatted": "scott ollivier"
    },
    "twitter": {
      "proof": {
        "url": "https://twitter.com/sjollivier/status/533665487633129472"
      },
      "username": "sjollivier"
    },
    "v": "0.2",
    "website": "http://www.linkedin.com/in/scottollivier"
  },
  "verifications": [
    {
      "identifier": "sjollivier",
      "proof_url": "https://gist.github.com/sjollivier/4bf6dce23197ce6efef0",
      "service": "github",
      "valid": true
    },
    {
      "identifier": "sjollivier",
      "proof_url": "https://twitter.com/sjollivier/status/533665487633129472",
      "service": "twitter",
      "valid": true
    },
    {
      "identifier": "scott.ollivier",
      "proof_url": "https://facebook.com/scott.ollivier/posts/10152901739289015",
      "service": "facebook",
      "valid": false
    }
  ]
}
