{
  "owner_address": "19ejvz1TniEH1qR7jAShoya3qeXcsr9Mpi",
  "profile": {
    "avatar": {
      "url": "https://s3.amazonaws.com/kd4/chrispecoraro"
    },
    "bio": "-Experienced, degreed web application developer @ @analyticsseo\n-Author & open-source contributor\n-Passionate about biomedical informatics & machine translation",
    "cover": {
      "url": "https://s3.amazonaws.com/dx3/chrispecoraro"
    },
    "facebook": {
      "proof": {
        "url": "https://facebook.com/chrispecoraro/posts/10153393774863087"
      },
      "username": "chrispecoraro"
    },
    "github": {
      "proof": {
        "url": "https://gist.github.com/chrispecoraro/ae13b4e70cdb76c9a16c"
      },
      "username": "chrispecoraro"
    },
    "location": {
      "formatted": "Palermo, Italy"
    },
    "name": {
      "formatted": "Christopher Pecoraro"
    },
    "twitter": {
      "proof": {
        "url": "https://twitter.com/chris__pecoraro/status/685375591311347712"
      },
      "username": "chris__pecoraro"
    },
    "v": "0.2",
    "website": "http://chrispecoraro.com"
  },
  "verifications": [
    {
      "identifier": "chrispecoraro",
      "proof_url": "https://gist.github.com/chrispecoraro/ae13b4e70cdb76c9a16c",
      "service": "github",
      "valid": true
    },
    {
      "identifier": "chris__pecoraro",
      "proof_url": "https://twitter.com/chris__pecoraro/status/685375591311347712",
      "service": "twitter",
      "valid": true
    },
    {
      "identifier": "chrispecoraro",
      "proof_url": "https://facebook.com/chrispecoraro/posts/10153393774863087",
      "service": "facebook",
      "valid": false
    }
  ]
}
