{
  "owner_address": "175wgWb9V6vAfiwQNEKxY8DsbKcar7mSo5",
  "profile": {
    "avatar": {
      "url": "https://s3.amazonaws.com/kd4/christianeg"
    },
    "bio": "Founder of a few startups and some other stuff.   RT ≠ Endorsement Contact me at christianeg@gmail.com",
    "cover": {
      "url": "https://s3.amazonaws.com/dx3/christianeg"
    },
    "location": {
      "formatted": "Madrid, Spain"
    },
    "name": {
      "formatted": "christian"
    },
    "twitter": {
      "proof": {
        "url": "https://twitter.com/christianeg/status/699472680295276544"
      },
      "username": "christianeg"
    },
    "v": "0.2",
    "website": "http://www.christianerburu.com"
  },
  "verifications": [
    {
      "identifier": "christianeg",
      "proof_url": "https://twitter.com/christianeg/status/699472680295276544",
      "service": "twitter",
      "valid": true
    }
  ]
}
